GeneMethyl/BetavalueDistribution.py
GeneMethyl/SimpleCutoff.py
GeneMethyl/TopPercentageCutoff.py
GeneMethyl/__init__.py
GeneMethyl-1.0.0.dist-info/LICENSE
GeneMethyl-1.0.0.dist-info/METADATA
GeneMethyl-1.0.0.dist-info/WHEEL
GeneMethyl-1.0.0.dist-info/top_level.txt
GeneMethyl-1.0.0.dist-info/RECORD
